chipcard/__init__.py
chipcard/card/__init__.py
chipcard/card/abstract.py
chipcard/card/openpgp.py
chipcard/pcsc/__init__.py
chipcard/pcsc/client.py
chipcard/pcsc/const.py
chipcard/pcsc/exception.py
chipcard/pcsc/proto.py
chipcard/pcsc/server.py
chipcard-0.1.0.dist-info/LICENSE
chipcard-0.1.0.dist-info/WHEEL
chipcard-0.1.0.dist-info/METADATA
chipcard-0.1.0.dist-info/RECORD
