Metadata-Version: 2.1
Name: chipcard
Version: 0.1.0
Summary: Python package to access chipcards
Home-page: https://github.com/joernheissler/chipcard
License: MIT
Keywords: chipcard,pcsc,smartcard,ISO-7816
Author: Jörn Heissler
Author-email: nosuchaddress@joern.heissler.de
Requires-Python: >=3.7,<4.0
Classifier: License :: OSI Approved :: MIT License
Classifier: Programming Language :: Python :: 3
Classifier: Programming Language :: Python :: 3.7
Classifier: Programming Language :: Python :: 3.8
Classifier: Programming Language :: Python :: 3.9
Classifier: Topic :: Security :: Cryptography
Classifier: Topic :: Software Development :: Libraries :: Python Modules
Provides-Extra: docs
Requires-Dist: anyio (>=2.0.2,<3.0.0)
Requires-Dist: asn1crypto (>=1.3.0,<2.0.0)
Requires-Dist: lazy (>=1.4,<2.0)
Project-URL: Repository, https://github.com/joernheissler/chipcard
